anubis/__init__.py
anubis/__main__.py
anubis/_version.py
anubis/common.py
anubis/collectors/__init__.py
anubis/collectors/base_collector.py
anubis/collectors/binexport.py
anubis/collectors/class_dump.py
anubis/collectors/nm.py
anubis/collectors/objc_protocol_selectors.py
anubis/collectors/plist.py
anubis/collectors/regs_tracker.py
anubis/collectors/rg.py
anubis/collectors/section.py
anubis/collectors/strings.py
anubis/ida_rpyc/__init__.py
anubis/ida_rpyc/dsc_stuff.py
anubis/ida_rpyc/ida_client.py
anubis/ida_rpyc/ida_server.py
anubis/ida_rpyc/regs_tracker/__init__.py
anubis/ida_rpyc/regs_tracker/disassembler.py
anubis/ida_rpyc/regs_tracker/exceptions.py
anubis/ida_rpyc/regs_tracker/ida_reg_tracker.py
anubis_ipsw-0.0.5.dist-info/METADATA
anubis_ipsw-0.0.5.dist-info/WHEEL
anubis_ipsw-0.0.5.dist-info/entry_points.txt
anubis_ipsw-0.0.5.dist-info/top_level.txt
anubis_ipsw-0.0.5.dist-info/RECORD
