Metadata-Version: 2.4
Name: anubis-ipsw
Version: 0.0.5
Summary: IPSW rule base collector
Author-email: netanelc305 <netanelc305@protonmail.com>
Maintainer-email: netanelc305 <netanelc305@protonmail.com>
Keywords: ios,jailbreak,cli,automation,darwin,osx,macos,ipsw
Classifier: Operating System :: iOS
Classifier: Operating System :: MacOS
Classifier: Development Status :: 5 - Production/Stable
Classifier: License :: OSI Approved :: GNU General Public License v3 or later (GPLv3+)
Classifier: Programming Language :: Python :: 3
Classifier: Programming Language :: Python :: 3.10
Classifier: Programming Language :: Python :: 3.11
Classifier: Programming Language :: Python :: 3.12
Classifier: Programming Language :: Python :: 3.13
Classifier: Programming Language :: Python :: 3 :: Only
Requires-Python: >=3.10
Requires-Dist: click
Requires-Dist: coloredlogs
Requires-Dist: python-binexport
Requires-Dist: rpyc
Requires-Dist: PyYAML
Requires-Dist: plumbum
Requires-Dist: idascript
Requires-Dist: tqdm
